lytils/__init__.py
lytils/app.py
lytils/classes/__init__.py
lytils/classes/Regex.py
lytils/common.py
lytils/discord/__init__.py
lytils/discord/DiscordBot.py
lytils/email/__init__.py
lytils/email/Email.py
lytils/file.py
lytils/google_sheets/__init__.py
lytils/google_sheets/Columns.py
lytils/google_sheets/errors.py
lytils/google_sheets/format.py
lytils/google_sheets/GoogleSheets.py
lytils/google_sheets/helpers.py
lytils/google_sheets/Range.py
lytils/google_sheets/Spreadsheet.py
lytils/google_sheets/SpreadsheetTab.py
lytils/google_sheets/validation.py
lytils/imports.py
lytils/input.py
lytils/log_html.py
lytils/logger.py
lytils/print.py
lytils/regex.py
lytils/response.py
lytils/surfshark.py
lytils-0.6.1.dist-info/LICENSE
lytils-0.6.1.dist-info/METADATA
lytils-0.6.1.dist-info/WHEEL
lytils-0.6.1.dist-info/RECORD
